MegamanicEdit
